scompiler/__init__.py
scompiler/__main__.py
scompiler/message.py
scompiler/run_script.py
scompiler/utils.py
scompiler/filetype/__init__.py
scompiler/filetype/filetype.py
scompiler/filetype/latex.py
scompiler/filetype/mbed.py
scompiler/filetype/python.py
scompiler/options/__init__.py
scompiler/options/args.py
scompiler/options/config.py
scompiler/options/options.py
scompiler-2.0.dist-info/licenses/LICENSE
scompiler-2.0.dist-info/METADATA
scompiler-2.0.dist-info/WHEEL
scompiler-2.0.dist-info/entry_points.txt
scompiler-2.0.dist-info/top_level.txt
scompiler-2.0.dist-info/RECORD
