Metadata-Version: 2.4
Name: scompiler
Version: 2.0
Summary: Simple program to compile, run and save code
License: The MIT License (MIT)
Project-URL: Homepage, https://gitlab.com/HansvonHohenstaufen/scompiler.git
Classifier: Development Status :: 5 - Production/Stable
Classifier: Intended Audience :: Developers
Classifier: Operating System :: POSIX :: Linux
Classifier: Programming Language :: Python
Classifier: Programming Language :: Python :: 3.13
Requires-Python: >=3.13
License-File: LICENSE
Requires-Dist: setuptools
Dynamic: license-file
